MANIFEST.in
config.py
driver.py
setup.py
utils.py
action/Action.py
action/__init__.py
bin/qingcloud
phantooom_qingcloud_cli.egg-info/PKG-INFO
phantooom_qingcloud_cli.egg-info/SOURCES.txt
phantooom_qingcloud_cli.egg-info/dependency_links.txt
phantooom_qingcloud_cli.egg-info/entry_points.txt
phantooom_qingcloud_cli.egg-info/requires.txt
phantooom_qingcloud_cli.egg-info/top_level.txt