Metadata-Version: 1.0
Name: phantooom-qingcloud-cli
Version: 0.1
Summary: homework-qingcluod-cli
Home-page: http://fullstack.love
Author: phantooom
Author-email: zouruixp@sina.com
License: MIT
Keywords: homework
Platform: UNKNOWN
